easyML/__init__.py
easyML/base_class.py
easyML/data.py
easyML/feature_engineering.py
easyML/genericmodelclass.py
easyML/models_classification.py
easyML/preprocess.py
easyML/tests/__init__.py
easyML/tests/conftest.py
easyML/tests/test_preprocess.py
easyML-0.1.0.dist-info/DESCRIPTION.rst
easyML-0.1.0.dist-info/METADATA
easyML-0.1.0.dist-info/RECORD
easyML-0.1.0.dist-info/WHEEL
easyML-0.1.0.dist-info/metadata.json
easyML-0.1.0.dist-info/top_level.txt
