Metadata-Version: 2.0
Name: easyML
Version: 0.1.0
Summary: A package designed to streamline the process of analyzing data using predictive models from scikit-learn's implementation.
Home-page: https://github.com/aarshayj/easyML
Author: Aarshay Jain
Author-email: aarshay.jain@columbia.edu
License: BSD
Platform: UNKNOWN
Classifier: Development Status :: 3 - Alpha
Classifier: Environment :: Console
Classifier: Intended Audience :: Science/Research
Classifier: Intended Audience :: Education
Classifier: Natural Language :: English
Classifier: License :: OSI Approved :: BSD License
Classifier: Programming Language :: Python
Classifier: Programming Language :: Python :: 2.7
Classifier: Programming Language :: Python :: 3.4
Classifier: Programming Language :: Python :: 3.5
Classifier: Topic :: Scientific/Engineering :: Information Analysis
Classifier: Topic :: Software Development :: Libraries :: Python Modules
Requires-Dist: cycler (>=0.10.0)
Requires-Dist: matplotlib (>=1.5.3)
Requires-Dist: numpy (>=1.11.3)
Requires-Dist: pandas (>=0.19.2)
Requires-Dist: py (>=1.4.32)
Requires-Dist: pyparsing (>=2.1.10)
Requires-Dist: python-dateutil (>=2.6.0)
Requires-Dist: pytz (>=2016.10)
Requires-Dist: scikit-learn (>=0.18)
Requires-Dist: scipy (>=0.18.1)
Requires-Dist: six (>=1.10.0)
